switchbotPatched
