Metadata-Version: 2.1
Name: switchbotPatched
Version: 0.13.6
Summary: A Unofficial library to communicate with Switchbot
Home-page: https://github.com/Switchbot-Python/pySwitchbot-patched
Author: Ninad
Author-email: ninadpchaudhari@gmail.com
License: MIT
Platform: UNKNOWN
Classifier: Development Status :: 3 - Alpha
Classifier: Environment :: Other Environment
Classifier: Intended Audience :: Developers
Classifier: Operating System :: OS Independent
Classifier: Programming Language :: Python
Classifier: Topic :: Home Automation
Classifier: Topic :: Software Development :: Libraries :: Python Modules
License-File: LICENSE
